cumulus_library_umls/__init__.py
cumulus_library_umls/ancillary_tables.sql
cumulus_library_umls/manifest.toml
cumulus_library_umls/static_builder.py
cumulus_library_umls/umls_builder.py
cumulus_library_umls/reference_sql/static_builder.sql
cumulus_library_umls/reference_sql/umls_builder.sql
cumulus_library_umls/static_files/SemGroups_2018.txt
cumulus_library_umls/static_files/SemanticTypes_2018AB.txt
cumulus_library_umls/static_files/umls_rel.tsv
cumulus_library_umls/static_files/umls_rela.tsv
cumulus_library_umls/static_files/umls_tty.tsv
cumulus_library_umls/static_files/umls_tui.tsv
cumulus_library_umls-0.3.3.dist-info/WHEEL
cumulus_library_umls-0.3.3.dist-info/METADATA
cumulus_library_umls-0.3.3.dist-info/RECORD
