Metadata-Version: 2.4
Name: cumulus-library-umls
Version: 0.3.3
Summary: A Unified Medical Language System® Metathesaurus study for the Cumulus project
Keywords: FHIR,SQL,Health Informatics
Requires-Python: >= 3.11
Classifier: License :: OSI Approved :: Apache Software License
Classifier: Operating System :: OS Independent
Classifier: Programming Language :: Python :: 3
Classifier: Topic :: Software Development :: Libraries :: Python Modules
Requires-Dist: cumulus-library >= 4.1.3
Requires-Dist: platformdirs >= 4.3.8
Requires-Dist: ruff < 0.13 ; extra == "dev"
Requires-Dist: pre-commit ; extra == "dev"
Requires-Dist: pytest ; extra == "test"
Requires-Dist: responses ; extra == "test"
Project-URL: Documentation, https://docs.smarthealthit.org/cumulus/
Project-URL: Home, https://smarthealthit.org/cumulus
Project-URL: Source, https://github.com/smart-on-fhir/cumulus-library-umls
Provides-Extra: dev
Provides-Extra: test
